ChangeLog
LICENSE
MANIFEST.in
README.md
setup.py
test.py
dkim/__init__.py
dkim/__main__.py
dkim/arcsign.py
dkim/arcverify.py
dkim/asn1.py
dkim/asyncsupport.py
dkim/canonicalization.py
dkim/crypto.py
dkim/dkimsign.py
dkim/dkimverify.py
dkim/dknewkey.py
dkim/dnsplug.py
dkim/util.py
dkim/tests/__init__.py
dkim/tests/test_arc.py
dkim/tests/test_canonicalization.py
dkim/tests/test_crypto.py
dkim/tests/test_dkim.py
dkim/tests/test_dkim_ed25519.py
dkim/tests/test_dkim_generate.py
dkim/tests/test_dkim_rsavariants.py
dkim/tests/test_dkim_tlsrpt.py
dkim/tests/test_dnsplug.py
dkim/tests/test_util.py
dkim/tests/data/1024_testkey.key
dkim/tests/data/1024_testkey_wo_markers.pub.rsa.txt
dkim/tests/data/1024_testkey_wo_markers.pub.txt
dkim/tests/data/2048_testkey.key
dkim/tests/data/2048_testkey_PKCS8.key
dkim/tests/data/2048_testkey_PKCS8.key.pub.txt
dkim/tests/data/2048_testkey_wo_markers.pub.rsa.txt
dkim/tests/data/2048_testkey_wo_markers.pub.txt
dkim/tests/data/badk.txt
dkim/tests/data/badversion.txt
dkim/tests/data/ed25519test.dns
dkim/tests/data/ed25519test.key
dkim/tests/data/ed25519test.msg
dkim/tests/data/ed25519test2.msg
dkim/tests/data/eximtest.dns
dkim/tests/data/message.mbox
dkim/tests/data/rfc6376.msg
dkim/tests/data/rfc6376.signed.msg
dkim/tests/data/rfc6376.signed.no_t.msg
dkim/tests/data/rfc6376.signed.rsa.msg
dkim/tests/data/rfc6376.w1258.msg
dkim/tests/data/rfc8032_7_1.key
dkim/tests/data/test.message
dkim/tests/data/test.message.baddomain
dkim/tests/data/test.private
dkim/tests/data/test.txt
dkim/tests/data/test2.message
dkim/tests/data/test2.private
dkim/tests/data/test2.txt
dkim/tests/data/test_bad.txt
dkim/tests/data/test_extra.message
dkim/tests/data/test_nofrom.message
dkim/tests/data/test_tlsrpt.txt
dkimpy.egg-info/PKG-INFO
dkimpy.egg-info/SOURCES.txt
dkimpy.egg-info/dependency_links.txt
dkimpy.egg-info/entry_points.txt
dkimpy.egg-info/not-zip-safe
dkimpy.egg-info/requires.txt
dkimpy.egg-info/top_level.txt
man/arcsign.1
man/arcverify.1
man/dkimsign.1
man/dkimverify.1
man/dknewkey.1