Metadata-Version: 2.1
Name: dkimpy
Version: 1.1.8
Summary: DKIM (DomainKeys Identified Mail), ARC (Authenticated Receive Chain), and TLSRPT (TLS Report) email signing and verification
Home-page: https://launchpad.net/dkimpy
Author: Scott Kitterman
Author-email: scott@kitterman.com
License: BSD-like
Classifier: Development Status :: 5 - Production/Stable
Classifier: Environment :: No Input/Output (Daemon)
Classifier: Intended Audience :: Developers
Classifier: License :: DFSG approved
Classifier: Natural Language :: English
Classifier: Operating System :: OS Independent
Classifier: Programming Language :: Python :: 3
Classifier: Topic :: Communications :: Email :: Mail Transport Agents
Classifier: Topic :: Communications :: Email :: Filters
Classifier: Topic :: Internet :: Name Service (DNS)
Classifier: Topic :: Software Development :: Libraries :: Python Modules
Provides-Extra: ARC
Provides-Extra: asyncio
Provides-Extra: ed25519
Provides-Extra: testing
License-File: LICENSE
